setup.py
math_add_fun/__init__.py
math_add_fun.egg-info/PKG-INFO
math_add_fun.egg-info/SOURCES.txt
math_add_fun.egg-info/dependency_links.txt
math_add_fun.egg-info/top_level.txt