Metadata-Version: 1.0
Name: math-add-fun
Version: 0.1
Summary: used for add and multipiltication
Home-page: UNKNOWN
Author: UNKNOWN
Author-email: UNKNOWN
License: UNKNOWN
Platform: UNKNOWN
